[{
    "type": "uPlot",
    "title": "Scatter",
    "uPlot": {
        "type": "scatter",
        "opt": {
            "pxAlign": false,
            "scales": {
                "x": {
                    "time": false,
                    "auto": true,
					"range": [0,10]
                },
                "y": {
                    "auto": true,
					"range": [0,10]
                }
            },
            "axes": [{
                "space": 30
            },{
				"space":30
			}],
            "cursor": {
                "show": true
            },
            "series": [{}, {}]
        }
    }
}]